src/__init__.py
src/slib_sorter.py
slib_sorter-1.6.7.dist-info/LICENSE
slib_sorter-1.6.7.dist-info/METADATA
slib_sorter-1.6.7.dist-info/WHEEL
slib_sorter-1.6.7.dist-info/entry_points.txt
slib_sorter-1.6.7.dist-info/top_level.txt
slib_sorter-1.6.7.dist-info/RECORD
