Metadata-Version: 2.1
Name: slib-sorter
Version: 1.6.7
Summary: A Python package for sorting Sample Libraries
Home-page: https://github.com/nrdrch/slib-sorter
Author: Lukas H
Author-email: fettkindasindauchoke@gmail.com
Classifier: Programming Language :: Python :: 3.7
Classifier: License :: OSI Approved :: Apache Software License
Classifier: Operating System :: Microsoft :: Windows :: Windows 10
License-File: LICENSE
Requires-Dist: termcolor (==2.3.0)
